odoo/addons/fieldservice_delivery/README.rst
odoo/addons/fieldservice_delivery/__init__.py
odoo/addons/fieldservice_delivery/__manifest__.py
odoo/addons/fieldservice_delivery/models/__init__.py
odoo/addons/fieldservice_delivery/models/fsm_order.py
odoo/addons/fieldservice_delivery/readme/CONFIGURE.rst
odoo/addons/fieldservice_delivery/readme/CONTRIBUTORS.rst
odoo/addons/fieldservice_delivery/readme/CREDITS.rst
odoo/addons/fieldservice_delivery/readme/DESCRIPTION.rst
odoo/addons/fieldservice_delivery/readme/INSTALL.rst
odoo/addons/fieldservice_delivery/readme/ROADMAP.rst
odoo/addons/fieldservice_delivery/readme/USAGE.rst
odoo/addons/fieldservice_delivery/static/description/icon.png
odoo/addons/fieldservice_delivery/static/description/index.html
odoo/addons/fieldservice_delivery/views/fsm_order.xml
odoo11_addon_fieldservice_delivery-11.0.0.0.1.99.dev3.dist-info/METADATA
odoo11_addon_fieldservice_delivery-11.0.0.0.1.99.dev3.dist-info/WHEEL
odoo11_addon_fieldservice_delivery-11.0.0.0.1.99.dev3.dist-info/top_level.txt
odoo11_addon_fieldservice_delivery-11.0.0.0.1.99.dev3.dist-info/RECORD
